Lab1-Counter/task3/counter.sv
module counter #(
    parameter WIDTH = 8
)(

    input logic              clk,  // Clock
    input logic              rst,  //reset
    input logic             ld, 
    input logic [WIDTH-1:0]  v, //value to preload
    output logic [WIDTH-1:0] count //count output
);

logic ld_last;

always_ff @ (posedge clk) 
    if (rst) begin
        count <= {WIDTH{1'b0}};
        ld_last <= 0;

    end else begin
        // Detect rising edge of ld
        if (ld && !ld_last)
            count <= count + {{WIDTH-1{1'b0}}, 1'b1}; // Increment on ld rising edge

        ld_last <= ld;
     end

endmodule

Lab1-Counter/task3/counter.vcd
$version Generated by VerilatedVcd $end
$date Wed Oct 30 23:46:32 2024 $end
$timescale 1ps $end

 $scope module TOP $end
  $var wire  1 # clk $end
  $var wire  8 ' count [7:0] $end
  $var wire  1 % ld $end
  $var wire  1 $ rst $end
  $var wire  8 & v [7:0] $end
  $scope module counter $end
   $var wire 32 ) WIDTH [31:0] $end
   $var wire  1 # clk $end
   $var wire  8 ' count [7:0] $end
   $var wire  1 % ld $end
   $var wire  1 ( ld_last $end
   $var wire  1 $ rst $end
   $var wire  8 & v [7:0] $end
  $upscope $end
 $upscope $end
$enddefinitions $end


#0
1#
1$
0%
b00000000 &
b00000000 '
0(
b00000000000000000000000000001000 )
#1
0#
#2
1#
#3
0#
#4
1#
#5
0#
#6
1#
0$
#7
0#
#8
1#
#9
0#
#10
1#
#11
0#
#12
1#
#13
0#
#14
1#
#15
0#
#16
1#
#17
0#
#18
1#
#19
0#
#20
1#
#21
0#
#22
1#
#23
0#
#24
1#
#25
0#
#26
1#
#27
0#
#28
1#
#29
0#
#30
1#
#31
0#
#32
1#
1$
#33
0#
#34
1#
0$
#35
0#
#36
1#
#37
0#
#38
1#
#39
0#
#40
1#
#41
0#
#42
1#
#43
0#
#44
1#
#45
0#
#46
1#
#47
0#
#48
1#
#49
0#
#50
1#
#51
0#
#52
1#
#53
0#
#54
1#
1%
b00110011 &
#55
0#
#56
1#
b00000001 '
1(
#57
0#
#58
1#
#59
0#
#60
1#
#61
0#
#62
1#
#63
0#
#64
1#
#65
0#
#66
1#
#67
0#
#68
1#
#69
0#
#70
1#
#71
0#
#72
1#
#73
0#
#74
1#
#75
0#
#76
1#
0%
#77
0#
#78
1#
0(
#79
0#
#80
1#
#81
0#
#82
1#
#83
0#
#84
1#
#85
0#
#86
1#
#87
0#
#88
1#
#89
0#
#90
1#
#91
0#
#92
1#
#93
0#
#94
1#
#95
0#
#96
1#
#97
0#
#98
1#
1%
#99
0#
#100
1#
b00000010 '
1(
#101
0#
#102
1#
#103
0#
#104
1#
#105
0#
#106
1#
#107
0#
#108
1#
#109
0#
#110
1#
#111
0#
#112
1#
#113
0#
#114
1#
#115
0#
#116
1#
0%
#117
0#
#118
1#
0(
#119
0#
#120
1#
#121
0#
#122
1#
#123
0#
#124
1#
#125
0#
#126
1#
#127
0#
#128
1#
#129
0#
#130
1#
#131
0#
#132
1#
#133
0#
#134
1#
1%
#135
0#
#136
1#
b00000011 '
1(
#137
0#
#138
1#
#139
0#
#140
1#
#141
0#
#142
1#
#143
0#
#144
1#
#145
0#
#146
1#
#147
0#
#148
1#
#149
0#
#150
1#
#151
0#
#152
1#
0%
#153
0#
#154
1#
0(
#155
0#
#156
1#
#157
0#
#158
1#
#159
0#
#160
1#
#161
0#
#162
1#
#163
0#
#164
1#
#165
0#
#166
1#
#167
0#
#168
1#
#169
0#
#170
1#
#171
0#
#172
1#
#173
0#
#174
1#
#175
0#
#176
1#
#177
0#
#178
1#
1%
#179
0#
#180
1#
b00000100 '
1(
#181
0#
#182
1#
#183
0#
#184
1#
#185
0#
#186
1#
#187
0#
#188
1#
#189
0#
#190
1#
#191
0#
#192
1#
0%
#193
0#
#194
1#
0(
#195
0#
#196
1#
#197
0#
#198
1#
#199
0#
#200
1#
#201
0#
#202
1#
#203
0#
#204
1#
#205
0#
#206
1#
#207
0#
#208
1#
#209
0#
#210
1#
1%
#211
0#
#212
1#
b00000101 '
1(
#213
0#
#214
1#
#215
0#
#216
1#
#217
0#
#218
1#
#219
0#
#220
1#
#221
0#
#222
1#
#223
0#
#224
1#
#225
0#
#226
1#
#227
0#
#228
1#
0%
#229
0#
#230
1#
0(
#231
0#
#232
1#
#233
0#
#234
1#
#235
0#
#236
1#
#237
0#
#238
1#
#239
0#
#240
1#
#241
0#
#242
1#
#243
0#
#244
1#
#245
0#
#246
1#
#247
0#
#248
1#
#249
0#
#250
1#
#251
0#
#252
1#
1%
#253
0#
#254
1#
b00000110 '
1(
#255
0#
#256
1#
#257
0#
#258
1#
#259
0#
#260
1#
#261
0#
#262
1#
#263
0#
#264
1#
#265
0#
#266
1#
#267
0#
#268
1#
#269
0#
#270
1#
#271
0#
#272
1#
#273
0#
#274
1#
#275
0#
#276
1#
#277
0#
#278
1#
#279
0#
#280
1#
#281
0#
#282
1#
#283
0#
#284
1#
0%
#285
0#
#286
1#
0(
#287
0#
#288
1#
#289
0#
#290
1#
#291
0#
#292
1#
#293
0#
#294
1#
#295
0#
#296
1#
1%
#297
0#
#298
1#
b00000111 '
1(
#299
0#
#300
1#
#301
0#
#302
1#
0%
#303
0#
#304
1#
0(
#305
0#
#306
1#
#307
0#
#308
1#
#309
0#
#310
1#
#311
0#
#312
1#
#313
0#
#314
1#
#315
0#
#316
1#
#317
0#
#318
1#
1%
#319
0#
#320
1#
b00001000 '
1(
#321
0#
#322
1#
#323
0#
#324
1#
#325
0#
#326
1#
#327
0#
#328
1#
#329
0#
#330
1#
#331
0#
#332
1#
0%
#333
0#
#334
1#
0(
#335
0#
#336
1#
#337
0#
#338
1#
#339
0#
#340
1#
#341
0#
#342
1#
#343
0#
#344
1#
#345
0#
#346
1#
1%
#347
0#
#348
1#
b00001001 '
1(
#349
0#
#350
1#
#351
0#
#352
1#
#353
0#
#354
1#
#355
0#
#356
1#
#357
0#
#358
1#
#359
0#
#360
1#
0%
#361
0#
#362
1#
0(
#363
0#
#364
1#
#365
0#
#366
1#
#367
0#
#368
1#
#369
0#
#370
1#
#371
0#
#372
1#
#373
0#
#374
1#
#375
0#
#376
1#
#377
0#
#378
1#
1%
#379
0#
#380
1#
0%
b00001010 '
1(
#381
0#
#382
1#
0(
#383
0#
#384
1#
1%
#385
0#
#386
1#
0%
b00001011 '
1(
#387
0#
#388
1#
0(
#389
0#
#390
1#
#391
0#
#392
1#
#393
0#
#394
1#
#395
0#
#396
1#
#397
0#
#398
1#
#399
0#
#400
1#
#401
0#
#402
1#
#403
0#
#404
1#
#405
0#
#406
1#
#407
0#
#408
1#
#409
0#
#410
1#
#411
0#
#412
1#
#413
0#
#414
1#
#415
0#
#416
1#
#417
0#
#418
1#
1%
#419
0#
#420
1#
b00001100 '
1(
#421
0#
#422
1#
#423
0#
#424
1#
#425
0#
#426
1#
#427
0#
#428
1#
0%
#429
0#
#430
1#
0(
#431
0#
#432
1#
#433
0#
#434
1#
#435
0#
#436
1#
#437
0#
#438
1#
#439
0#
#440
1#
#441
0#
#442
1#
#443
0#
#444
1#
1%
#445
0#
#446
1#
b00001101 '
1(
#447
0#
#448
1#
#449
0#
#450
1#
#451
0#
#452
1#
#453
0#
#454
1#
#455
0#
#456
1#
#457
0#
#458
1#
0%
#459
0#
#460
1#
0(
#461
0#
#462
1#
#463
0#
#464
1#
#465
0#
#466
1#
#467
0#
#468
1#
#469
0#
#470
1#
#471
0#
#472
1#
#473
0#
#474
1#
#475
0#
#476
1#
#477
0#
#478
1#
#479
0#
#480
1#
#481
0#
#482
1#
1%
#483
0#
#484
1#
0%
b00001110 '
1(
#485
0#
#486
1#
0(
#487
0#
#488
1#
1%
#489
0#
#490
1#
b00001111 '
1(
#491
0#
#492
1#
#493
0#
#494
1#
0%
#495
0#
#496
1#
0(
#497
0#
#498
1#
#499
0#
#500
1#
#501
0#
#502
1#
#503
0#
#504
1#
#505
0#
#506
1#
#507
0#
#508
1#
#509
0#
#510
1#
1%
#511
0#
#512
1#
0%
b00010000 '
1(
#513
0#
#514
1#
0(
#515
0#
#516
1#
#517
0#
#518
1#
#519
0#
#520
1#
#521
0#
#522
1#
#523
0#
#524
1#
#525
0#
#526
1#
#527
0#
#528
1#
1%
#529
0#
#530
1#
b00010001 '
1(
#531
0#
#532
1#
#533
0#
#534
1#
#535
0#
#536
1#
#537
0#
#538
1#
0%
#539
0#
#540
1#
0(
#541
0#
#542
1#
#543
0#
#544
1#
#545
0#
#546
1#
#547
0#
#548
1#
#549
0#
#550
1#
#551
0#
#552
1#
#553
0#
#554
1#
#555
0#
#556
1#
#557
0#
#558
1#
#559
0#
#560
1#
#561
0#
#562
1#
1%
#563
0#
#564
1#
b00010010 '
1(
#565
0#
#566
1#
#567
0#
#568
1#
#569
0#
#570
1#
#571
0#
#572
1#
#573
0#
#574
1#
#575
0#
#576
1#
#577
0#
#578
1#
#579
0#
#580
1#
0%
#581
0#
#582
1#
0(
